google_contact_local/__init__.py
google_contact_local/google_contacts.py
google_contact_local/google_contacts_constants.py
google_contact_local/google_contacts_push.py
google_contact_local/google_contacts_sync.py
google_contact_local/user_external_databse_schema_backward_compatible.py
google_contact_local-0.0.62.dist-info/METADATA
google_contact_local-0.0.62.dist-info/WHEEL
google_contact_local-0.0.62.dist-info/top_level.txt
google_contact_local-0.0.62.dist-info/RECORD
