Metadata-Version: 2.4
Name: google-contact-local
Version: 0.0.62
Summary: PyPI Package for Circles google-contact-local Python
Home-page: https://github.com/circles-zone/google-contact-local-python-package
Author: Circles
Author-email: valeria.e@circ.zone
Classifier: Programming Language :: Python :: 3
Classifier: License :: Other/Proprietary License
Classifier: Operating System :: OS Independent
Requires-Dist: google-account-local>=0.0.11
Requires-Dist: pycountry
Requires-Dist: tzdata>=2024.1
Requires-Dist: api-management-local>=0.0.63
Requires-Dist: contact-email-address-local>=0.0.8
Requires-Dist: contact-group-local>=0.0.30
Requires-Dist: contact-local>=0.0.42
Requires-Dist: contact-location-local>=0.0.14
Requires-Dist: contact-notes-local>=0.0.33
Requires-Dist: contact-persons-local>=0.0.8
Requires-Dist: contact-phone-local>=0.0.12
Requires-Dist: contact-profile-local>=0.0.7
Requires-Dist: contact-user-external-local>=0.0.1
Requires-Dist: database-mysql-local>=0.1.1
Requires-Dist: importer-local>=0.0.54
Requires-Dist: internet-domain-local>=0.0.8
Requires-Dist: location-local>=0.0.104
Requires-Dist: logger-local>=0.0.135
Requires-Dist: organization-profile-local>=0.0.4
Requires-Dist: organizations-local>=0.0.14
Requires-Dist: python-sdk-remote>=0.0.93
Requires-Dist: url-remote>=0.0.91
Requires-Dist: user-context-remote>=0.0.75
Requires-Dist: user-external-local>=0.0.42
Dynamic: author
Dynamic: author-email
Dynamic: classifier
Dynamic: description
Dynamic: description-content-type
Dynamic: home-page
Dynamic: requires-dist
Dynamic: summary
